Metadata-Version: 2.1
Name: odoo9-addon-sale-order-lot-selection
Version: 9.0.1.1.0
Summary: Sale Order Lot Selection
Home-page: http://www.agilebg.com
Author: Odoo Community Association (OCA), Agile Business Group
Author-email: support@odoo-community.org
License: AGPL-3
Platform: UNKNOWN
Classifier: Programming Language :: Python
Classifier: Framework :: Odoo
Classifier: License :: OSI Approved :: GNU Affero General Public License v3
Requires-Python: ~=2.7
Requires-Dist: odoo (<9.1a,>=9.0a)
